LICENSE
MANIFEST.in
README.md
requirements.in
requirements.txt
setup.py
hca_ingest/__init__.py
hca_ingest.egg-info/PKG-INFO
hca_ingest.egg-info/SOURCES.txt
hca_ingest.egg-info/dependency_links.txt
hca_ingest.egg-info/requires.txt
hca_ingest.egg-info/top_level.txt
hca_ingest/api/__init__.py
hca_ingest/api/ingestapi.py
hca_ingest/api/requests_utils.py
hca_ingest/api/stagingapi.py
hca_ingest/downloader/__init__.py
hca_ingest/downloader/data_collector.py
hca_ingest/downloader/downloader.py
hca_ingest/downloader/entity.py
hca_ingest/downloader/flattener.py
hca_ingest/downloader/schema_collector.py
hca_ingest/downloader/schema_url.py
hca_ingest/downloader/workbook.py
hca_ingest/importer/__init__.py
hca_ingest/importer/data_node.py
hca_ingest/importer/importer.py
hca_ingest/importer/conversion/__init__.py
hca_ingest/importer/conversion/column_specification.py
hca_ingest/importer/conversion/conversion_strategy.py
hca_ingest/importer/conversion/data_converter.py
hca_ingest/importer/conversion/exceptions.py
hca_ingest/importer/conversion/metadata_entity.py
hca_ingest/importer/conversion/template_manager.py
hca_ingest/importer/conversion/utils.py
hca_ingest/importer/spreadsheet/__init__.py
hca_ingest/importer/spreadsheet/ingest_workbook.py
hca_ingest/importer/spreadsheet/ingest_worksheet.py
hca_ingest/importer/submission/__init__.py
hca_ingest/importer/submission/entity.py
hca_ingest/importer/submission/entity_linker.py
hca_ingest/importer/submission/entity_map.py
hca_ingest/importer/submission/errors.py
hca_ingest/importer/submission/ingest_submitter.py
hca_ingest/importer/submission/submission.py
hca_ingest/template/__init__.py
hca_ingest/template/descriptor.py
hca_ingest/template/exceptions.py
hca_ingest/template/linked_spreadsheet_builder.py
hca_ingest/template/migration_parser.py
hca_ingest/template/schema_parser.py
hca_ingest/template/schema_template.py
hca_ingest/template/spreadsheet_builder.py
hca_ingest/template/tab_config.py
hca_ingest/template/vanilla_spreadsheet_builder.py
hca_ingest/utils/IngestError.py
hca_ingest/utils/__init__.py
hca_ingest/utils/bundlevalidator.py
hca_ingest/utils/date.py
hca_ingest/utils/doctict.py
