Metadata-Version: 2.1
Name: hca-ingest
Version: 2.8.1
Summary: A library to communicate with the Human Cell Atlas ingest API hosted by the EBI for creation and management of HCA project submissions.
Home-page: https://github.com/ebi-ait/ingest-client
License-File: LICENSE
